mcp_server.py
aliases/__init__.py
aliases/filename_alias_tools.py
aspose_words_mcp-0.1.6.dist-info/licenses/LICENSE
core/__init__.py
core/comments.py
core/content.py
core/export.py
core/io.py
core/layout.py
core/links.py
core/notes.py
core/properties.py
core/protection.py
core/reading.py
core/store.py
core/styles.py
core/tables.py
core/watermarks.py
core/utils/__init__.py
core/utils/docs_util.py
core/utils/license.py
aspose_words_mcp-0.1.6.dist-info/METADATA
aspose_words_mcp-0.1.6.dist-info/WHEEL
aspose_words_mcp-0.1.6.dist-info/entry_points.txt
aspose_words_mcp-0.1.6.dist-info/top_level.txt
aspose_words_mcp-0.1.6.dist-info/RECORD
