Metadata-Version: 2.4
Name: aspose-words-mcp
Version: 0.1.6
Summary: MCP server for Aspose.Words automation (FastMCP-based)
Author-email: Aspose <support@aspose.com>
License: MIT License
Project-URL: Documentation, https://github.com/aspose-words/Aspose.Words-MCP-Server#readme
Project-URL: Repository, https://github.com/aspose-words/Aspose.Words-MCP-Server
Project-URL: Free Support, https://forum.aspose.com/c/words/8
Keywords: MCP,Aspose,Aspose.Words,Word,DOCX,PDF,server
Classifier: Development Status :: 3 - Alpha
Classifier: License :: OSI Approved :: MIT License
Classifier: Programming Language :: Python
Classifier: Programming Language :: Python :: 3
Classifier: Programming Language :: Python :: 3.11
Classifier: Programming Language :: Python :: 3.12
Classifier: Programming Language :: Python :: 3.13
Classifier: Operating System :: OS Independent
Classifier: Topic :: Office/Business
Classifier: Topic :: Software Development :: Libraries :: Python Modules
Requires-Python: <3.14,>=3.11
License-File: LICENSE
Requires-Dist: fastmcp
Requires-Dist: aspose-words>=25.11.0
Dynamic: license-file
